radical/asyncflow/__init__.py
radical/asyncflow/constants.py
radical/asyncflow/data.py
radical/asyncflow/errors.py
radical/asyncflow/logging.py
radical/asyncflow/utils.py
radical/asyncflow/workflow_manager.py
radical/asyncflow/backends/__init__.py
radical/asyncflow/backends/execution/__init__.py
radical/asyncflow/backends/execution/base.py
radical/asyncflow/backends/execution/concurrent.py
radical/asyncflow/backends/execution/dask_parallel.py
radical/asyncflow/backends/execution/noop.py
radical/asyncflow/backends/execution/radical_pilot.py
radical_asyncflow-0.2.0.dist-info/licenses/LICENSE
radical_asyncflow-0.2.0.dist-info/METADATA
radical_asyncflow-0.2.0.dist-info/WHEEL
radical_asyncflow-0.2.0.dist-info/top_level.txt
radical_asyncflow-0.2.0.dist-info/RECORD
