Metadata-Version: 2.4
Name: radical.asyncflow
Version: 0.2.0
Summary: A High Performance Asynchronous Workflow Scripting Library
Author: RADICAL Lab
Author-email: Aymen Alsaadi <aymen.alsaadi@rutgers.edu>
Maintainer-email: Aymen Alsaadi <aymen.alsaadi@rutgers.edu>
Project-URL: Homepage, https://github.com/radical-cybertools/radical.asyncflow
Project-URL: Issues, https://github.com/radical-cybertools/radical.asyncflow/issues
Project-URL: Documentation, https://radical-cybertools.github.io/radical.asyncflow
Requires-Python: >=3.9
License-File: LICENSE
Requires-Dist: pydantic
Requires-Dist: typeguard
Requires-Dist: requests
Provides-Extra: dask
Requires-Dist: dask[distributed]; extra == "dask"
Provides-Extra: radicalpilot
Requires-Dist: radical.pilot; extra == "radicalpilot"
Provides-Extra: lint
Requires-Dist: ruff; extra == "lint"
Provides-Extra: dev
Requires-Dist: pytest; extra == "dev"
Requires-Dist: pytest-asyncio; extra == "dev"
Requires-Dist: pytest-cov; extra == "dev"
Provides-Extra: doc
Requires-Dist: mkdocs==1.5.3; extra == "doc"
Requires-Dist: mkdocs-material==9.5.9; extra == "doc"
Requires-Dist: mkdocstrings[python]>=0.26.1; extra == "doc"
Requires-Dist: mkdocs-gen-files==0.5.0; extra == "doc"
Requires-Dist: mkdocs-literate-nav==0.6.1; extra == "doc"
Requires-Dist: mkdocs-section-index==0.3.8; extra == "doc"
Requires-Dist: mkdocs-glightbox; extra == "doc"
Requires-Dist: mkdocs-material-extensions; extra == "doc"
Requires-Dist: mkdocs-minify-plugin; extra == "doc"
Dynamic: license-file
